<annotation>
	<folder>images</folder>
	<filename>225.jpg</filename>
	<path>/home/evgeniy/Development/hackaton/beer_detector/images/225.jpg</path>
	<source>
		<database>Unknown</database>
	</source>
	<size>
		<width>100</width>
		<height>100</height>
		<depth>1</depth>
	</size>
	<segmented>0</segmented>
	<object>
		<name>beer</name>
		<pose>Unspecified</pose>
		<truncated>0</truncated>
		<difficult>0</difficult>
		<bndbox>
			<xmin>32</xmin>
			<ymin>4</ymin>
			<xmax>47</xmax>
			<ymax>79</ymax>
		</bndbox>
	</object>
</annotation>
